PyDreamCheeky-1.0.0b2.dist-info/DESCRIPTION.rst
PyDreamCheeky-1.0.0b2.dist-info/RECORD
PyDreamCheeky-1.0.0b2.dist-info/METADATA
PyDreamCheeky-1.0.0b2.dist-info/metadata.json
PyDreamCheeky-1.0.0b2.dist-info/WHEEL
PyDreamCheeky-1.0.0b2.dist-info/top_level.txt
py_dream_cheeky/button.py
py_dream_cheeky/__init__.py
