Metadata-Version: 2.0
Name: PyDreamCheeky
Version: 1.0.0b2
Summary: A convenient Python driver for Dream Cheeky's Big Red Button
Home-page: https://github.com/Simon-Tang/py_dream_cheeky
Author: Simon Tang
Author-email: simontang@live.ca
License: Unlicense
Keywords: dream cheeky big red button usb driver
Platform: UNKNOWN
Classifier: Development Status :: 4 - Beta
Classifier: Operating System :: Microsoft :: Windows
Classifier: Operating System :: MacOS :: MacOS X
Classifier: Operating System :: Unix
Classifier: Programming Language :: Python :: 3
Classifier: Intended Audience :: Developers
Classifier: Topic :: System :: Hardware :: Hardware Drivers
Requires-Dist: pyusb
